{"0.01": {"10": {"MP_SP": [0.08, 0.27], "MR_SR": [0.04, 0.14], "MF_SF": [0.05, 0.18]}, "100": {"MP_SP": [0.09, 0.27], "MR_SR": [0.05, 0.15], "MF_SF": [0.06, 0.19]}, "500": {"MP_SP": [0.09, 0.26], "MR_SR": [0.08, 0.21], "MF_SF": [0.08, 0.2]}, "1000": {"MP_SP": [0.08, 0.2], "MR_SR": [0.11, 0.25], "MF_SF": [0.09, 0.2]}, "2000": {"MP_SP": [0.09, 0.22], "MR_SR": [0.12, 0.29], "MF_SF": [0.1, 0.23]}}, "0.05": {"10": {"MP_SP": [0.02, 0.14], "MR_SR": [0.01, 0.07], "MF_SF": [0.01, 0.09]}, "100": {"MP_SP": [0.03, 0.16], "MR_SR": [0.03, 0.16], "MF_SF": [0.03, 0.13]}, "500": {"MP_SP": [0.04, 0.17], "MR_SR": [0.05, 0.18], "MF_SF": [0.04, 0.14]}, "1000": {"MP_SP": [0.04, 0.16], "MR_SR": [0.06, 0.24], "MF_SF": [0.04, 0.18]}, "2000": {"MP_SP": [0.03, 0.12], "MR_SR": [0.06, 0.24], "MF_SF": [0.04, 0.16]}}}